mypackage/__init__.py
mypackage/run.py
rh_airflow_utils-0.0.1.dist-info/METADATA
rh_airflow_utils-0.0.1.dist-info/WHEEL
rh_airflow_utils-0.0.1.dist-info/top_level.txt
rh_airflow_utils-0.0.1.dist-info/RECORD
